tests/__init__.py
tests/test_read.py
tse_index/__init__.py
tse_index/_utils.py
tse_index/settings.py
tse_index/tse.py
tse_index/tse_scrapper.py
tse_index-0.0.4.dist-info/LICENSE
tse_index-0.0.4.dist-info/METADATA
tse_index-0.0.4.dist-info/WHEEL
tse_index-0.0.4.dist-info/top_level.txt
tse_index-0.0.4.dist-info/RECORD
