Metadata-Version: 2.1
Name: tse-index
Version: 0.0.4
Summary: Indices of Tehran Stock Exchange
Home-page: https://github.com/alised/tse-index
Author: Alised
Author-email: seddighi.ali@gmail.com
License: UNKNOWN
Project-URL: Bug Tracker, https://github.com/alised/tse-index/issues
Platform: UNKNOWN
Classifier: Programming Language :: Python :: 3
Classifier: License :: OSI Approved :: GNU General Public License v3 (GPLv3)
Classifier: Operating System :: OS Independent
Requires-Python: >=3.6
License-File: LICENSE
Requires-Dist: numpy (>=1.20.3)
Requires-Dist: pandas (>=1.3.2)
Requires-Dist: jdatetime (>=3.6.2)
Requires-Dist: requests (>=2.26.0)
Requires-Dist: beautifulsoup4 (>=4.10.0)
Requires-Dist: lxml (>=4.6.3)
